dejaq/__init__.py
dejaq/parallel.py
dejaq/queues.py
dejaq/remote.py
dejaq/stream.py
dejaq-0.7.0.dist-info/licenses/LICENSE.md
dejaq-0.7.0.dist-info/METADATA
dejaq-0.7.0.dist-info/WHEEL
dejaq-0.7.0.dist-info/top_level.txt
dejaq-0.7.0.dist-info/RECORD
