Metadata-Version: 2.4
Name: dejaq
Version: 0.7.0
Summary: Déjà Queue – A fast multiprocessing queue for Python
Author: jlab.berlin, Benjamin Judkewitz
License: MIT
Project-URL: Homepage, https://github.com/danionella/dejaq
Project-URL: Documentation, https://danionella.github.io/dejaq/
Keywords: multiprocessing,queue
Requires-Python: >=3.8
License-File: LICENSE.md
Requires-Dist: numpy
Requires-Dist: tqdm
Requires-Dist: psutil
Requires-Dist: cloudpickle
Requires-Dist: posix_ipc; platform_system != "Windows"
Requires-Dist: pywin32; platform_system == "Windows"
Dynamic: license-file
